pytorch_optimizer/__init__.py
pytorch_optimizer/base/__init__.py
pytorch_optimizer/base/exception.py
pytorch_optimizer/base/optimizer.py
pytorch_optimizer/base/scheduler.py
pytorch_optimizer/base/type.py
pytorch_optimizer/loss/__init__.py
pytorch_optimizer/loss/bi_tempered.py
pytorch_optimizer/loss/cross_entropy.py
pytorch_optimizer/loss/dice.py
pytorch_optimizer/loss/f1.py
pytorch_optimizer/loss/focal.py
pytorch_optimizer/loss/jaccard.py
pytorch_optimizer/loss/ldam.py
pytorch_optimizer/loss/lovasz.py
pytorch_optimizer/loss/tversky.py
pytorch_optimizer/lr_scheduler/__init__.py
pytorch_optimizer/lr_scheduler/chebyshev.py
pytorch_optimizer/lr_scheduler/cosine_anealing.py
pytorch_optimizer/lr_scheduler/experimental/__init__.py
pytorch_optimizer/lr_scheduler/experimental/deberta_v3_lr_scheduler.py
pytorch_optimizer/lr_scheduler/linear_warmup.py
pytorch_optimizer/lr_scheduler/proportion.py
pytorch_optimizer/lr_scheduler/rex.py
pytorch_optimizer/lr_scheduler/wsd.py
pytorch_optimizer/optimizer/__init__.py
pytorch_optimizer/optimizer/a2grad.py
pytorch_optimizer/optimizer/adabelief.py
pytorch_optimizer/optimizer/adabound.py
pytorch_optimizer/optimizer/adadelta.py
pytorch_optimizer/optimizer/adafactor.py
pytorch_optimizer/optimizer/adagc.py
pytorch_optimizer/optimizer/adahessian.py
pytorch_optimizer/optimizer/adai.py
pytorch_optimizer/optimizer/adalite.py
pytorch_optimizer/optimizer/adam_mini.py
pytorch_optimizer/optimizer/adamax.py
pytorch_optimizer/optimizer/adamc.py
pytorch_optimizer/optimizer/adamg.py
pytorch_optimizer/optimizer/adamod.py
pytorch_optimizer/optimizer/adamp.py
pytorch_optimizer/optimizer/adams.py
pytorch_optimizer/optimizer/adamw.py
pytorch_optimizer/optimizer/adan.py
pytorch_optimizer/optimizer/adanorm.py
pytorch_optimizer/optimizer/adapnm.py
pytorch_optimizer/optimizer/adashift.py
pytorch_optimizer/optimizer/adasmooth.py
pytorch_optimizer/optimizer/ademamix.py
pytorch_optimizer/optimizer/adopt.py
pytorch_optimizer/optimizer/agc.py
pytorch_optimizer-3.9.0.dist-info/METADATA
pytorch_optimizer-3.9.0.dist-info/WHEEL
pytorch_optimizer-3.9.0.dist-info/licenses/LICENSE
pytorch_optimizer-3.9.0.dist-info/RECORD
