Metadata-Version: 2.4
Name: pytorch_optimizer
Version: 3.9.0
Summary: optimizer & lr scheduler & objective function collections in PyTorch
License: Apache-2.0
License-File: LICENSE
Keywords: pytorch,deep-learning,optimizer,lr scheduler,A2Grad,Alice,ASGD,AccSGD,AdaBelief,AdaBound,AdaDelta,AdaFactor,AdaGC,AdaMax,AdaMuon,AdamG,AdaMod,AdaNorm,AdaPNM,AdaSmooth,AdEMAMix,Simplified-AdEMAMix,ADOPT,AdaHessian,Adai,Adalite,AdaLomo,AdamMini,AdamP,AdamS,Adan,AggMo,Aida,AliG,Amos,Apollo,APOLLO,AvaGrad,bSAM,BCOS,CAME,Conda,DAdaptAdaGrad,DAdaptAdam,DAdaptAdan,DAdaptSGD,DAdaptLion,DeMo,DiffGrad,EmoFact,EmoLynx,EmoNavi,EmoNeco,EmoZeal,EXAdam,FAdam,Fira,FOCUS,FriendlySAM,Fromage,FTRL,GaLore
Author: kozistr
Author-email: kozistr@gmail.com
Maintainer: kozistr
Maintainer-email: kozistr@gmail.com
Requires-Python: >=3.8
Classifier: Development Status :: 5 - Production/Stable
Classifier: Intended Audience :: Developers
Classifier: Intended Audience :: Education
Classifier: Intended Audience :: Science/Research
Classifier: License :: OSI Approved :: Apache Software License
Classifier: Operating System :: OS Independent
Classifier: Programming Language :: Python :: 3
Classifier: Programming Language :: Python :: 3.8
Classifier: Programming Language :: Python :: 3.9
Classifier: Programming Language :: Python :: 3.10
Classifier: Programming Language :: Python :: 3.11
Classifier: Programming Language :: Python :: 3.12
Classifier: Programming Language :: Python :: 3.13
Classifier: Programming Language :: Python :: 3.14
Classifier: Topic :: Scientific/Engineering
Classifier: Topic :: Scientific/Engineering :: Artificial Intelligence
Classifier: Topic :: Software Development
Classifier: Topic :: Software Development :: Libraries
Classifier: Topic :: Software Development :: Libraries :: Python Modules
Requires-Dist: numpy (<=1.24.4) ; python_version < "3.9"
Requires-Dist: numpy (>1.24.4) ; python_version >= "3.9"
Requires-Dist: torch (>=1.10) ; python_version >= "3.10"
Requires-Dist: torch (>=1.10,<2.5) ; python_version < "3.9"
Requires-Dist: torch (>=1.10,<2.9) ; python_version == "3.9"
Project-URL: Documentation, https://pytorch-optimizers.readthedocs.io/en/latest
Project-URL: Homepage, https://github.com/kozistr/pytorch_optimizer
Project-URL: Repository, https://github.com/kozistr/pytorch_optimizer
